signa/__init__.py
signa/core.py
signa/logger.py
signa/providers/__init__.py
signa/providers/aws.py
signa/providers/b2.py
signa/providers/dospaces.py
signa/providers/oss.py
signa/providers/s3.py
signa/providers/yaobject.py
tests/__init__.py
signa-0.3.0.dist-info/LICENSE
signa-0.3.0.dist-info/METADATA
signa-0.3.0.dist-info/WHEEL
signa-0.3.0.dist-info/top_level.txt
signa-0.3.0.dist-info/RECORD
