Metadata-Version: 2.1
Name: signa
Version: 0.3.0
Summary: One lib to sign them all.
Home-page: https://github.com/05bit/python-signa
Author: Alexey Kinëv
Author-email: rudy@05bit.com
License: MIT License
Platform: UNKNOWN
Classifier: Development Status :: 3 - Alpha
Classifier: Environment :: Console
Classifier: Environment :: Web Environment
Classifier: Intended Audience :: Developers
Classifier: License :: OSI Approved :: MIT License
Classifier: Programming Language :: Python :: 3
